iridiumSBD/__init__.py
iridiumSBD/cli.py
iridiumSBD/iridiumSBD.py
iridiumSBD/directip/__init__.py
iridiumSBD/directip/server.py
iridiumSBD-0.0.8.dist-info/AUTHORS.rst
iridiumSBD-0.0.8.dist-info/LICENSE
iridiumSBD-0.0.8.dist-info/METADATA
iridiumSBD-0.0.8.dist-info/WHEEL
iridiumSBD-0.0.8.dist-info/entry_points.txt
iridiumSBD-0.0.8.dist-info/top_level.txt
iridiumSBD-0.0.8.dist-info/RECORD
