Metadata-Version: 2.1
Name: iridiumSBD
Version: 0.0.8
Summary: Communication system for Iridium Short Burst Data Service.
Home-page: https://github.com/castelao/isbd
Author: Guilherme Castelão
Author-email: guilherme@castelao.net
License: BSD license
Keywords: isbd
Platform: UNKNOWN
Classifier: Development Status :: 2 - Pre-Alpha
Classifier: Intended Audience :: Developers
Classifier: License :: OSI Approved :: BSD License
Classifier: Natural Language :: English
Classifier: Programming Language :: Python :: 2
Classifier: Programming Language :: Python :: 2.7
Classifier: Programming Language :: Python :: 3
Classifier: Programming Language :: Python :: 3.4
Classifier: Programming Language :: Python :: 3.5
Classifier: Programming Language :: Python :: 3.6
Requires-Dist: Click (>=6.7)
Requires-Dist: psycopg2 (>=2.6)
